{
  "name" : "PropertiesOfShapesUsingDateOfBirth",
  "description" : "all of the data model properties for entities that have a property df a data of birth",
  "resultFormat" : "OBJECT",
  "select" : {
    "filter" : {
      "property" : {
        "@id" : "http://www.w3.org/ns/shacl#property"
      },
      "valueObject" : {
        "property" : {
          "@id" : "http://www.w3.org/ns/shacl#path"
        },
        "valueConcept" : [ {
          "@id" : "http://endhealth.info/im#dateOfBirth"
        } ]
      }
    },
    "entityType" : {
      "@id" : "http://www.w3.org/ns/shacl#NodeShape"
    },
    "property" : [ {
      "@id" : "http://www.w3.org/ns/shacl#property",
      "object" : {
        "property" : [ {
          "binding" : "*"
        } ]
      }
    } ]
  },
  "usePrefixes" : true
}