{
  "entities" : [ {
    "iri" : "http://endhealth.info/im#Folder",
    "http://www.w3.org/2000/01/rdf-schema#label" : "Folder",
    "http://www.w3.org/ns/shacl#property" : [ {
      "bn" : "genid-c9d973dea08045738c3b09d759af641332-b1343",
      "http://www.w3.org/ns/shacl#path" : {
        "iri" : "http://www.w3.org/2000/01/rdf-schema#label"
      }
    }, {
      "bn" : "genid-c9d973dea08045738c3b09d759af641332-b1344",
      "http://www.w3.org/ns/shacl#path" : {
        "iri" : "http://www.w3.org/2000/01/rdf-schema#comment"
      }
    }, {
      "bn" : "genid-c9d973dea08045738c3b09d759af641332-b1345",
      "http://www.w3.org/ns/shacl#path" : {
        "iri" : "http://www.w3.org/1999/02/22-rdf-syntax-ns#type"
      }
    }, {
      "bn" : "genid-c9d973dea08045738c3b09d759af641332-b1346",
      "http://www.w3.org/ns/shacl#path" : {
        "iri" : "http://endhealth.info/im#status"
      }
    }, {
      "bn" : "genid-c9d973dea08045738c3b09d759af641332-b1347",
      "http://www.w3.org/ns/shacl#path" : {
        "iri" : "http://endhealth.info/im#scheme"
      }
    }, {
      "bn" : "genid-c9d973dea08045738c3b09d759af641332-b1348",
      "http://www.w3.org/ns/shacl#path" : {
        "iri" : "http://endhealth.info/im#isContainedIn"
      }
    }, {
      "bn" : "genid-c9d973dea08045738c3b09d759af641332-b1349",
      "http://www.w3.org/ns/shacl#path" : {
        "iri" : "http://endhealth.info/im#contentType"
      }
    } ]
  }, {
    "iri" : "http://endhealth.info/im#CohortQuery",
    "http://www.w3.org/2000/01/rdf-schema#label" : "Cohort Query",
    "http://www.w3.org/ns/shacl#property" : [ {
      "bn" : "genid-c9d973dea08045738c3b09d759af641332-b37",
      "http://www.w3.org/ns/shacl#path" : {
        "iri" : "http://www.w3.org/2000/01/rdf-schema#label"
      }
    }, {
      "bn" : "genid-c9d973dea08045738c3b09d759af641332-b38",
      "http://www.w3.org/ns/shacl#path" : {
        "iri" : "http://www.w3.org/2000/01/rdf-schema#comment"
      }
    }, {
      "bn" : "genid-c9d973dea08045738c3b09d759af641332-b39",
      "http://www.w3.org/ns/shacl#path" : {
        "iri" : "http://www.w3.org/1999/02/22-rdf-syntax-ns#type"
      }
    }, {
      "bn" : "genid-c9d973dea08045738c3b09d759af641332-b40",
      "http://www.w3.org/ns/shacl#path" : {
        "iri" : "http://endhealth.info/im#status"
      }
    }, {
      "bn" : "genid-c9d973dea08045738c3b09d759af641332-b41",
      "http://www.w3.org/ns/shacl#path" : {
        "iri" : "http://endhealth.info/im#scheme"
      }
    }, {
      "bn" : "genid-c9d973dea08045738c3b09d759af641332-b42",
      "http://www.w3.org/ns/shacl#path" : {
        "iri" : "http://endhealth.info/im#isContainedIn"
      }
    }, {
      "bn" : "genid-c9d973dea08045738c3b09d759af641332-b43",
      "http://www.w3.org/ns/shacl#path" : {
        "iri" : "http://endhealth.info/im#definition"
      }
    }, {
      "bn" : "genid-c9d973dea08045738c3b09d759af641332-b44",
      "http://www.w3.org/ns/shacl#path" : {
        "iri" : "http://endhealth.info/im#returnType"
      }
    } ]
  }, {
    "iri" : "http://endhealth.info/im#DatasetQuery",
    "http://www.w3.org/2000/01/rdf-schema#label" : "Dataset Query",
    "http://www.w3.org/ns/shacl#property" : [ {
      "bn" : "genid-c9d973dea08045738c3b09d759af641332-b45",
      "http://www.w3.org/ns/shacl#path" : {
        "iri" : "http://www.w3.org/2000/01/rdf-schema#label"
      }
    }, {
      "bn" : "genid-c9d973dea08045738c3b09d759af641332-b46",
      "http://www.w3.org/ns/shacl#path" : {
        "iri" : "http://www.w3.org/2000/01/rdf-schema#comment"
      }
    }, {
      "bn" : "genid-c9d973dea08045738c3b09d759af641332-b47",
      "http://www.w3.org/ns/shacl#path" : {
        "iri" : "http://www.w3.org/1999/02/22-rdf-syntax-ns#type"
      }
    }, {
      "bn" : "genid-c9d973dea08045738c3b09d759af641332-b48",
      "http://www.w3.org/ns/shacl#path" : {
        "iri" : "http://endhealth.info/im#status"
      }
    }, {
      "bn" : "genid-c9d973dea08045738c3b09d759af641332-b49",
      "http://www.w3.org/ns/shacl#path" : {
        "iri" : "http://endhealth.info/im#scheme"
      }
    }, {
      "bn" : "genid-c9d973dea08045738c3b09d759af641332-b50",
      "http://www.w3.org/ns/shacl#path" : {
        "iri" : "http://endhealth.info/im#isContainedIn"
      }
    }, {
      "bn" : "genid-c9d973dea08045738c3b09d759af641332-b51",
      "http://www.w3.org/ns/shacl#path" : {
        "iri" : "http://endhealth.info/im#definition"
      }
    } ]
  } ]
}